rubin_jupyter_utils/config/__init__.py
rubin_jupyter_utils/config/_version.py
rubin_jupyter_utils/config/rubinconfig.py
rubin_jupyter_utils.config-0.33.0.dist-info/LICENSE
rubin_jupyter_utils.config-0.33.0.dist-info/METADATA
rubin_jupyter_utils.config-0.33.0.dist-info/WHEEL
rubin_jupyter_utils.config-0.33.0.dist-info/top_level.txt
rubin_jupyter_utils.config-0.33.0.dist-info/RECORD
