Metadata-Version: 2.1
Name: rubin-jupyter-utils.config
Version: 0.33.0
Summary: UNKNOWN
Home-page: https://github.com/lsst-sqre/rubin-jupyter-config
Author: Adam Thornton
Author-email: athornton@lsst.org
License: MIT
Keywords: rubin,jupyter,config
Platform: UNKNOWN
Classifier: Development Status :: 4 - Beta
Classifier: Programming Language :: Python :: 3.6
Classifier: License :: OSI Approved :: MIT License
Requires-Dist: eliot (<2,>=1)
Requires-Dist: eliot-tree (<20,>=19)
Requires-Dist: jupyter-client (<7,>=6)
Requires-Dist: rubin-jupyter-utils.helpers (<1.0,>=0.31.0)
